minos/networks/__init__.py
minos/networks/brokers/__init__.py
minos/networks/brokers/clients.py
minos/networks/brokers/collections/__init__.py
minos/networks/brokers/collections/queues/__init__.py
minos/networks/brokers/collections/queues/abc.py
minos/networks/brokers/collections/queues/database/__init__.py
minos/networks/brokers/collections/queues/database/factories.py
minos/networks/brokers/collections/queues/database/impl.py
minos/networks/brokers/collections/queues/memory.py
minos/networks/brokers/dispatchers/__init__.py
minos/networks/brokers/dispatchers/impl.py
minos/networks/brokers/dispatchers/requests.py
minos/networks/brokers/handlers/__init__.py
minos/networks/brokers/handlers/impl.py
minos/networks/brokers/handlers/ports.py
minos/networks/brokers/messages/__init__.py
minos/networks/brokers/messages/contextvars.py
minos/networks/brokers/messages/models/__init__.py
minos/networks/brokers/messages/models/abc.py
minos/networks/brokers/messages/models/v1.py
minos/networks/brokers/pools.py
minos/networks/brokers/publishers/__init__.py
minos/networks/brokers/publishers/abc.py
minos/networks/brokers/publishers/memory.py
minos/networks/brokers/publishers/queued/__init__.py
minos/networks/brokers/publishers/queued/impl.py
minos/networks/brokers/publishers/queued/queues/__init__.py
minos/networks/brokers/publishers/queued/queues/abc.py
minos/networks/brokers/publishers/queued/queues/database.py
minos/networks/brokers/publishers/queued/queues/memory.py
minos/networks/brokers/subscribers/__init__.py
minos/networks/brokers/subscribers/abc.py
minos/networks/brokers/subscribers/filtered/__init__.py
minos/networks/brokers/subscribers/filtered/impl.py
minos/networks/brokers/subscribers/filtered/validators/__init__.py
minos/networks/brokers/subscribers/filtered/validators/abc.py
minos/networks/brokers/subscribers/filtered/validators/duplicates/__init__.py
minos/networks/brokers/subscribers/filtered/validators/duplicates/abc.py
minos_microservice_networks-0.7.0.dist-info/LICENSE
minos_microservice_networks-0.7.0.dist-info/WHEEL
minos_microservice_networks-0.7.0.dist-info/METADATA
minos_microservice_networks-0.7.0.dist-info/RECORD
